gemini/__init__.py
gemini/codecommon.py
gemini/datastorage.py
gemini/gemini.py
llm_agregator-0.1.0.dist-info/LICENSE
llm_agregator-0.1.0.dist-info/METADATA
llm_agregator-0.1.0.dist-info/WHEEL
llm_agregator-0.1.0.dist-info/top_level.txt
llm_agregator-0.1.0.dist-info/RECORD
