Metadata-Version: 2.1
Name: llm-agregator
Version: 0.1.0
Summary: A package for generating diagrams using various models
Home-page: https://github.com/yourusername/your-repo
Author: Your Name
Author-email: your.email@example.com
Classifier: Programming Language :: Python :: 3
Classifier: License :: OSI Approved :: MIT License
Classifier: Operating System :: OS Independent
Requires-Python: >=3.6
License-File: LICENSE
Requires-Dist: google-generativeai
